tomclient/__init__.py
tomclient/client.py
tomclient/clock.py
tomclient/utility.py
tomclient/clients/__init__.py
tomclient/clients/jws_client.py
tomclient/clients/tom_client.py
tomclient/gpuml/__init__.py
tomclient/gpuml/gpu_profiler.py
tomclient/pods/__init__.py
tomclient/pods/config.py
tomclient/pods/manager.py
tomclient/pods/pod.py
tomclient/pods/utils.py
tomclient/states/__init__.py
tomclient/states/globals.py
tomclient-0.0.23.data/scripts/tom
tomclient-0.0.23.dist-info/METADATA
tomclient-0.0.23.dist-info/WHEEL
tomclient-0.0.23.dist-info/top_level.txt
tomclient-0.0.23.dist-info/RECORD
