Metadata-Version: 2.1
Name: tomclient
Version: 0.0.23
Summary: TOMClient is a client library for TOM
Author: Xiaozhe Yao
Author-email: askxzyao@gmail.com
Requires-Dist: typer
Requires-Dist: jsonrpc-websocket
Requires-Dist: netifaces
Requires-Dist: nvidia-ml-py
Requires-Dist: requests
Requires-Dist: loguru
Requires-Dist: rich
Requires-Dist: humanize
Requires-Dist: pyyaml
Requires-Dist: bkm
Requires-Dist: dstool
